mail_mcp/__init__.py
mail_mcp/cache.py
mail_mcp/config.py
mail_mcp/config_tool.py
mail_mcp/connection_pool.py
mail_mcp/errors.py
mail_mcp/imap_service.py
mail_mcp/main.py
mail_mcp/models.py
mail_mcp/performance.py
mail_mcp/server.py
mail_mcp/setup.py
mail_mcp/smtp_service.py
mail_mcp/utils.py
mail_mcp-2.1.0.dist-info/METADATA
mail_mcp-2.1.0.dist-info/WHEEL
mail_mcp-2.1.0.dist-info/entry_points.txt
mail_mcp-2.1.0.dist-info/top_level.txt
mail_mcp-2.1.0.dist-info/RECORD
