Metadata-Version: 2.4
Name: mail-mcp
Version: 2.1.0
Summary: High-performance MCP server for enterprise email management with trusted sender filtering, connection pooling, and intelligent caching
Author-email: Mail MCP Team <team@mail-mcp.dev>
License: MIT
Project-URL: Homepage, https://github.com/LupinLin1/mail-mcp
Project-URL: Repository, https://github.com/LupinLin1/mail-mcp
Project-URL: Issues, https://github.com/LupinLin1/mail-mcp/issues
Project-URL: Documentation, https://mail-mcp.dev
Keywords: mcp,email,imap,smtp,claude,claude-code,automation,trusted-senders,performance,security
Classifier: Development Status :: 5 - Production/Stable
Classifier: Intended Audience :: Developers
Classifier: Intended Audience :: System Administrators
Classifier: Operating System :: OS Independent
Classifier: Programming Language :: Python :: 3
Classifier: Programming Language :: Python :: 3.8
Classifier: Programming Language :: Python :: 3.9
Classifier: Programming Language :: Python :: 3.10
Classifier: Programming Language :: Python :: 3.11
Classifier: Programming Language :: Python :: 3.12
Classifier: Topic :: Communications :: Email
Classifier: Topic :: Software Development :: Libraries :: Python Modules
Classifier: Topic :: System :: Monitoring
Classifier: Topic :: Internet :: WWW/HTTP :: Dynamic Content
Requires-Python: >=3.8
Requires-Dist: fastmcp>=0.4.0
Requires-Dist: python-dotenv>=1.0.0
Requires-Dist: aiohttp>=3.8.0
Requires-Dist: click>=8.0.0
Requires-Dist: requests>=2.25.0
Requires-Dist: psutil>=5.8.0
Provides-Extra: dev
Requires-Dist: pytest>=7.0.0; extra == "dev"
Requires-Dist: pytest-asyncio>=0.21.0; extra == "dev"
Requires-Dist: black>=23.0.0; extra == "dev"
Requires-Dist: isort>=5.0.0; extra == "dev"
Requires-Dist: flake8>=6.0.0; extra == "dev"
Requires-Dist: build>=0.10.0; extra == "dev"
Requires-Dist: twine>=4.0.0; extra == "dev"
Provides-Extra: auto
Requires-Dist: pyyaml>=6.0; extra == "auto"
